README.md
setup.py
django_mysql_geventpool/__init__.py
django_mysql_geventpool/utils.py
django_mysql_geventpool.egg-info/PKG-INFO
django_mysql_geventpool.egg-info/SOURCES.txt
django_mysql_geventpool.egg-info/dependency_links.txt
django_mysql_geventpool.egg-info/requires.txt
django_mysql_geventpool.egg-info/top_level.txt
django_mysql_geventpool/backends/__init__.py
django_mysql_geventpool/backends/connection_pool.py
django_mysql_geventpool/backends/mysql/__init__.py
django_mysql_geventpool/backends/mysql/base.py
django_mysql_geventpool/backends/mysql/connection_pool.py
django_mysql_geventpool/backends/mysql/creation.py