Metadata-Version: 1.0
Name: django-mysql-geventpool
Version: 0.2.1
Summary: Add a MySQL connection pool for django using gevent
Home-page: UNKNOWN
Author: aihara
Author-email: aihara@argmax.jp
License: Apache 2.0
Platform: UNKNOWN
